ddocs/__init__.py
ddocs/__main__.py
ddocs/db.py
ddocs/gui.py
ddocs/modules.py
ddocs/fonts/OpenSans.ttf
ddocs/languages/javascript.txt
ddocs/languages/python.txt
ddocs-0.1.2.dist-info/METADATA
ddocs-0.1.2.dist-info/WHEEL
ddocs-0.1.2.dist-info/entry_points.txt
ddocs-0.1.2.dist-info/top_level.txt
ddocs-0.1.2.dist-info/RECORD
