Metadata-Version: 2.1
Name: ddocs
Version: 0.1.2
Author: gkegke
License: MIT
Project-URL: Homepage, https://github.com/gkegke/ddocs
Keywords: docs,library,offline,documentation
Classifier: License :: OSI Approved :: MIT License
Classifier: Programming Language :: Python
Classifier: Programming Language :: Python :: 3
Requires-Python: >=3.8
Requires-Dist: dearpygui
Requires-Dist: platformdirs
Provides-Extra: dev
Requires-Dist: pytest ; extra == 'dev'
